avocadopy/__init__.py
avocadopy/utils.py
avocadopy-0.0.2.dist-info/LICENSE
avocadopy-0.0.2.dist-info/METADATA
avocadopy-0.0.2.dist-info/WHEEL
avocadopy-0.0.2.dist-info/top_level.txt
avocadopy-0.0.2.dist-info/RECORD
