Metadata-Version: 2.1
Name: avocadopy
Version: 0.0.2
Summary: Tools for medical statistics.
Home-page: https://github.com/b-niu/avocadopy
Author: B Niu
Author-email: shinji006@126.com
License: UNKNOWN
Platform: UNKNOWN
Classifier: Programming Language :: Python :: 3
Classifier: License :: OSI Approved :: MIT License
Classifier: Operating System :: OS Independent
Requires-Python: >=3.6
